[
 {
   "House Number": 1,
   "Bedrooms": 2,
   "Restrooms": 1.5,
   "Sq. Ft.": 1003,
   "Year Built": 1989,
   "Price": 69000,
   "Down Payment": 6900,
   "Amount Financed": 62100,
   "Credit Score": "580-619",
   "Mortgage Payments": 360,
   "Insurance": 31,
   "Taxes": 165,
   "Utilities": 240,
   "Total Monthly Payment": 796
 },
 {
   "House Number": 1,
   "Bedrooms": 2,
   "Restrooms": 1.5,
   "Sq. Ft.": 1003,
   "Year Built": 1989,
   "Price": 69000,
   "Down Payment": 6900,
   "Amount Financed": 62100,
   "Credit Score": "620-699",
   "Mortgage Payments": 345,
   "Insurance": 31,
   "Taxes": 165,
   "Utilities": 240,
   "Total Monthly Payment": 781
 },
 {
   "House Number": 1,
   "Bedrooms": 2,
   "Restrooms": 1.5,
   "Sq. Ft.": 1003,
   "Year Built": 1989,
   "Price": 69000,
   "Down Payment": 6900,
   "Amount Financed": 62100,
   "Credit Score": "700-850",
   "Mortgage Payments": 325,
   "Insurance": 31,
   "Taxes": 165,
   "Utilities": 240,
   "Total Monthly Payment": 761
 },
 {
   "House Number": 2,
   "Bedrooms": 3,
   "Restrooms": 1.5,
   "Sq. Ft.": 1774,
   "Year Built": 1993,
   "Price": 109900,
   "Down Payment": 10990,
   "Amount Financed": 98910,
   "Credit Score": "580-619",
   "Mortgage Payments": 540,
   "Insurance": 51,
   "Taxes": 226,
   "Utilities": 280,
   "Total Monthly Payment": 1097
 },
 {
   "House Number": 2,
   "Bedrooms": 3,
   "Restrooms": 1.5,
   "Sq. Ft.": 1774,
   "Year Built": 1993,
   "Price": 109900,
   "Down Payment": 10990,
   "Amount Financed": 98910,
   "Credit Score": "620-699",
   "Mortgage Payments": 525,
   "Insurance": 51,
   "Taxes": 226,
   "Utilities": 280,
   "Total Monthly Payment": 1082
 },
 {
   "House Number": 2,
   "Bedrooms": 3,
   "Restrooms": 1.5,
   "Sq. Ft.": 1774,
   "Year Built": 1993,
   "Price": 109900,
   "Down Payment": 10990,
   "Amount Financed": 98910,
   "Credit Score": "700-850",
   "Mortgage Payments": 512,
   "Insurance": 51,
   "Taxes": 226,
   "Utilities": 280,
   "Total Monthly Payment": 1069
 },
 {
   "House Number": 3,
   "Bedrooms": 4,
   "Restrooms": 2.5,
   "Sq. Ft.": 2008,
   "Year Built": 1998,
   "Price": 224900,
   "Down Payment": 22490,
   "Amount Financed": 202410,
   "Credit Score": "580-619",
   "Mortgage Payments": 1105,
   "Insurance": 105,
   "Taxes": 451,
   "Utilities": 300,
   "Total Monthly Payment": 1961
 },
 {
   "House Number": 3,
   "Bedrooms": 4,
   "Restrooms": 2.5,
   "Sq. Ft.": 2008,
   "Year Built": 1998,
   "Price": 224900,
   "Down Payment": 22490,
   "Amount Financed": 202410,
   "Credit Score": "620-699",
   "Mortgage Payments": 1074,
   "Insurance": 105,
   "Taxes": 451,
   "Utilities": 300,
   "Total Monthly Payment": 1930
 },
 {
   "House Number": 3,
   "Bedrooms": 4,
   "Restrooms": 2.5,
   "Sq. Ft.": 2008,
   "Year Built": 1998,
   "Price": 224900,
   "Down Payment": 22490,
   "Amount Financed": 202410,
   "Credit Score": "700-850",
   "Mortgage Payments": 1047,
   "Insurance": 105,
   "Taxes": 451,
   "Utilities": 300,
   "Total Monthly Payment": 1903
 },
 {
   "House Number": 4,
   "Bedrooms": 5,
   "Restrooms": 4.5,
   "Sq. Ft.": 4462,
   "Year Built": 2008,
   "Price": 519800,
   "Down Payment": 51980,
   "Amount Financed": 467820,
   "Credit Score": "580-619",
   "Mortgage Payments": 2554,
   "Insurance": 242,
   "Taxes": 865,
   "Utilities": 445,
   "Total Monthly Payment": 4106
 },
 {
   "House Number": 4,
   "Bedrooms": 5,
   "Restrooms": 4.5,
   "Sq. Ft.": 4462,
   "Year Built": 2008,
   "Price": 519800,
   "Down Payment": 51980,
   "Amount Financed": 467820,
   "Credit Score": "620-699",
   "Mortgage Payments": 2483,
   "Insurance": 242,
   "Taxes": 865,
   "Utilities": 445,
   "Total Monthly Payment": 4035
 },
 {
   "House Number": 4,
   "Bedrooms": 5,
   "Restrooms": 4.5,
   "Sq. Ft.": 4462,
   "Year Built": 2008,
   "Price": 519800,
   "Down Payment": 51980,
   "Amount Financed": 467820,
   "Credit Score": "700-850",
   "Mortgage Payments": 2421,
   "Insurance": 242,
   "Taxes": 865,
   "Utilities": 445,
   "Total Monthly Payment": 3973
 }
]